{"assets":{"05DF17FDF1161610DBD29D7C9E74CCE3":{"type":"texture","index":1,"assetRequest":{"type":"slide","state":"incoming","slide":"0AD3EE2F-FFD0-42EA-94CB-5736076168B6"},"url":{"web":"assets/75A89BB6-B4FF-4B8D-AA7A-E6D2EA2A6E7E.svgmap"},"width":1280,"height":960},"26B7AC2E5EB2465A2249F255BE8489D9":{"type":"texture","index":0,"assetRequest":{"type":"slide","state":"outgoing","slide":"75A89BB6-B4FF-4B8D-AA7A-E6D2EA2A6E7E"},"url":{"web":"assets/75A89BB6-B4FF-4B8D-AA7A-E6D2EA2A6E7E.svgmap"},"width":1280,"height":960}},"events":[{"effects":[{"beginTime":0,"baseLayer":{"animations":[],"initialState":{"affineTransform":[1,0,0,1,0,0],"masksToBounds":false,"rotation":0,"scale":1,"position":{"pointX":640,"pointY":480},"width":1280,"sublayerTransform":[1,0,0,0,0,1,0,0,0,0,1,0,0,0,0,1],"contentsRect":{"y":0,"x":0,"width":1,"height":1},"opacity":1,"edgeAntialiasingMask":251658240,"height":960,"hidden":false,"anchorPoint":{"pointX":0.5,"pointY":0.5}},"objectID":"0","layers":[{"animations":[],"initialState":{"affineTransform":[1,0,0,1,0,0],"masksToBounds":false,"rotation":0,"scale":1,"position":{"pointX":640,"pointY":480},"width":1280,"sublayerTransform":[1,0,0,0,0,1,0,0,0,0,1,-0.0003938390152512299,0,0,0,1],"contentsRect":{"y":0,"x":0,"width":1,"height":1},"opacity":1,"edgeAntialiasingMask":251658240,"height":960,"hidden":false,"anchorPoint":{"pointX":0.5,"pointY":0.5}},"layers":[{"animations":[],"layers":[],"texturedRectangle":{"isBackgroundTexture":false,"singleTextureOpacity":1,"textureType":0,"textBaseline":0,"textXHeight":0,"isVerticalText":false},"initialState":{"affineTransform":[1,0,0,1,0,0],"masksToBounds":false,"rotation":0,"scale":1,"position":{"pointX":640,"pointY":480},"width":1280,"sublayerTransform":[1,0,0,0,0,1,0,0,0,0,1,0,0,0,0,1],"contentsRect":{"y":0,"x":0,"width":1,"height":1},"opacity":1,"edgeAntialiasingMask":0,"height":960,"hidden":false,"anchorPoint":{"pointX":0.5,"pointY":0.5}},"texture":"05DF17FDF1161610DBD29D7C9E74CCE3"},{"animations":[{"timeOffset":0,"from":{"scalar":false},"beginTime":0,"repeatCount":0,"fillMode":"both","property":"hidden","autoreverses":false,"duration":0.01,"to":{"scalar":true}}],"layers":[],"texturedRectangle":{"isBackgroundTexture":false,"singleTextureOpacity":1,"textureType":0,"textBaseline":0,"textXHeight":0,"isVerticalText":false},"initialState":{"affineTransform":[1,0,0,1,0,0],"masksToBounds":false,"rotation":0,"scale":1,"position":{"pointX":640,"pointY":480},"width":1280,"sublayerTransform":[1,0,0,0,0,1,0,0,0,0,1,0,0,0,0,1],"contentsRect":{"y":0,"x":0,"width":1,"height":1},"opacity":1,"edgeAntialiasingMask":0,"height":960,"hidden":false,"anchorPoint":{"pointX":0.5,"pointY":0.5}},"texture":"26B7AC2E5EB2465A2249F255BE8489D9"}]}]},"effects":[],"duration":0.01,"type":"transition","name":"none","objectID":"0"}],"automaticPlay":false,"hyperlinks":[],"accessibility":[{"text":"Donnez un maximum d’information aux futurs utilisateurs : prix, divers commentaires, lieu de RDV, etc…","targetRectangle":{"y":687.5999968817102,"x":19.78663121711566,"width":646.330078125,"height":117.5999979972839}},{"text":"image15.png","targetRectangle":{"y":120.1231460571289,"x":725.466552734375,"width":415.2152099609375,"height":737.0078735351562}},{"text":"Information sur le produit","targetRectangle":{"y":4.411573701280297,"x":149.7355558221773,"width":1039.927,"height":112}},{"text":"image14.png","targetRectangle":{"y":120.1231460571289,"x":124.7335433959961,"width":415.2152099609375,"height":737.0078735351562}},{"text":"et pour donner plus de visibilité, vous pouvez prendre en photo votre produit !!","targetRectangle":{"y":853.4116423895227,"x":605.8357635642226,"width":622.072265625,"height":117.5999979972839}}],"baseLayer":{"animations":[],"initialState":{"affineTransform":[1,0,0,1,0,0],"masksToBounds":false,"rotation":0,"scale":1,"position":{"pointX":640,"pointY":480},"width":1280,"sublayerTransform":[1,0,0,0,0,1,0,0,0,0,1,0,0,0,0,1],"contentsRect":{"y":0,"x":0,"width":1,"height":1},"opacity":1,"edgeAntialiasingMask":251658240,"height":960,"hidden":false,"anchorPoint":{"pointX":0.5,"pointY":0.5}},"objectID":"0","layers":[{"animations":[],"initialState":{"affineTransform":[1,0,0,1,0,0],"masksToBounds":false,"rotation":0,"scale":1,"position":{"pointX":640,"pointY":480},"width":1280,"sublayerTransform":[1,0,0,0,0,1,0,0,0,0,1,-0.0003938390152512299,0,0,0,1],"contentsRect":{"y":0,"x":0,"width":1,"height":1},"opacity":1,"edgeAntialiasingMask":251658240,"height":960,"hidden":false,"anchorPoint":{"pointX":0.5,"pointY":0.5}},"layers":[{"animations":[],"layers":[],"texturedRectangle":{"isBackgroundTexture":false,"singleTextureOpacity":1,"textureType":0,"textBaseline":0,"textXHeight":0,"isVerticalText":false},"initialState":{"affineTransform":[1,0,0,1,0,0],"masksToBounds":false,"rotation":0,"scale":1,"position":{"pointX":640,"pointY":480},"width":1280,"sublayerTransform":[1,0,0,0,0,1,0,0,0,0,1,0,0,0,0,1],"contentsRect":{"y":0,"x":0,"width":1,"height":1},"opacity":1,"edgeAntialiasingMask":0,"height":960,"hidden":false,"anchorPoint":{"pointX":0.5,"pointY":0.5}},"texture":"26B7AC2E5EB2465A2249F255BE8489D9"}]}]}}]}